filipid/__init__.py
filipid/list_ports.py
filipid/port.py
filipid-0.0.4.dist-info/METADATA
filipid-0.0.4.dist-info/WHEEL
filipid-0.0.4.dist-info/entry_points.txt
filipid-0.0.4.dist-info/top_level.txt
filipid-0.0.4.dist-info/RECORD
