Metadata-Version: 2.1
Name: filipid
Version: 0.0.4
Summary: UMAK utils module
Home-page: UNKNOWN
Author: Gavrilo Andric
Author-email: gavriloandric@gmail.com
License: UNKNOWN
Platform: UNKNOWN
Classifier: Programming Language :: Python :: 3
Classifier: Operating System :: OS Independent
Requires-Dist: pyserial (==3.4)
